{
	"backtraceGraph" : 
	{
		"commands" : 
		[
			"install"
		],
		"files" : 
		[
			"CMakeLists.txt"
		],
		"nodes" : 
		[
			{
				"file" : 0
			},
			{
				"command" : 0,
				"file" : 0,
				"line" : 176,
				"parent" : 0
			},
			{
				"command" : 0,
				"file" : 0,
				"line" : 180,
				"parent" : 0
			},
			{
				"command" : 0,
				"file" : 0,
				"line" : 200,
				"parent" : 0
			},
			{
				"command" : 0,
				"file" : 0,
				"line" : 205,
				"parent" : 0
			}
		]
	},
	"installers" : 
	[
		{
			"backtrace" : 1,
			"component" : "Unspecified",
			"destination" : "include",
			"paths" : 
			[
				{
					"from" : "include",
					"to" : "."
				}
			],
			"type" : "directory"
		},
		{
			"backtrace" : 2,
			"component" : "Unspecified",
			"destination" : "share/cmake/nlohmann_json",
			"paths" : 
			[
				"/Users/macbookpro/learn-c++/build/nlohmann_jsonConfig.cmake",
				"/Users/macbookpro/learn-c++/build/nlohmann_jsonConfigVersion.cmake"
			],
			"type" : "file"
		},
		{
			"backtrace" : 3,
			"component" : "Unspecified",
			"destination" : "share/cmake/nlohmann_json",
			"exportName" : "nlohmann_jsonTargets",
			"exportTargets" : 
			[
				{
					"id" : "nlohmann_json::@6890427a1f51a3e7e1df",
					"index" : 0
				}
			],
			"paths" : 
			[
				"CMakeFiles/Export/c5a95352faa8b09b394d8af6a01f43bc/nlohmann_jsonTargets.cmake"
			],
			"type" : "export"
		},
		{
			"backtrace" : 4,
			"component" : "Unspecified",
			"destination" : "share/pkgconfig",
			"paths" : 
			[
				"/Users/macbookpro/learn-c++/build/nlohmann_json.pc"
			],
			"type" : "file"
		}
	],
	"paths" : 
	{
		"build" : ".",
		"source" : "."
	}
}
